{
  "intro": "马云，男，1964年10月15日生于浙江省杭州市，祖籍浙江省嵊州市（原嵊县）谷来镇， 阿里巴巴集团主要创始人，现担任阿里巴巴集团董事局主席、日本软银董事、TNC（大自然保护协会）中国理事会主席兼全球董事会成员、华谊兄弟董事、生命科学突破奖基金会董事。1988年毕业于杭州师范学院外语系，同年担任杭州电子工学院英文及国际贸易教师，1995年创办中国第一家互联网商业信息发布网站“中国黄页”，1998年出任中国国际电子商务中心国富通信息技术发展有限公司总经理，1999年创办阿里巴巴，并担任阿里集团CEO、董事局主席，2013年5月10日，辞任阿里巴巴集团CEO，继续担任阿里集团董事局主席。2015年6月30日，马云当选全球互联网治理联盟理事会联合主席。",
  "gaikuang": {
      "name": "马云",
      "n_name": "风清扬（阿里内部的花名）",
      "birth":"1964年9月10日",
      "y_name":"Jackma",
      "from": "中华人民共和国",
      "zuji":"汉族",
      "birth_d": "浙江省杭州市"
  },
  
  "jian_intro" : "1999年辞去公职创办阿里巴巴网站, 2008年日本第十届企业家大奖, 2009中国经济十年商业领袖十人, 2012CCTV中国经济年度人物, 创立淘宝, 创立支付宝。中国第一首富。",

  "beijing": " 企业家",

  "school": "杭州师范学院，获外语学士学位",

  "images":[
            "image/yun.jpg",
            "image/yun1.jpg",
            "image/yun2.jpg",
            "image/yun3.jpg"
          ],

  "others": {

      "jiguan":"浙江嵊州谷来镇，后父母移居杭州",
      "xueli":"本科",
      "xuexing":"o型",
      "wife":"张英",
      "xingzuo":"处女座"

  }
 
}